datawhys_experimental_control/__init__.py
datawhys_experimental_control/_version.py
datawhys_experimental_control-0.1.2.data/data/share/jupyter/labextensions/datawhys_experimental_control/package.json
datawhys_experimental_control-0.1.2.data/data/share/jupyter/labextensions/datawhys_experimental_control/static/509.6453405b922c99906929.js
datawhys_experimental_control-0.1.2.data/data/share/jupyter/labextensions/datawhys_experimental_control/static/692.1fb5a7bda18d52b917e0.js
datawhys_experimental_control-0.1.2.data/data/share/jupyter/labextensions/datawhys_experimental_control/static/692.1fb5a7bda18d52b917e0.js.LICENSE.txt
datawhys_experimental_control-0.1.2.data/data/share/jupyter/labextensions/datawhys_experimental_control/static/728.831d83a24909d4006501.js
datawhys_experimental_control-0.1.2.data/data/share/jupyter/labextensions/datawhys_experimental_control/static/remoteEntry.4495fc5cf8d3fd7d51aa.js
datawhys_experimental_control-0.1.2.data/data/share/jupyter/labextensions/datawhys_experimental_control/static/style.js
datawhys_experimental_control-0.1.2.data/data/share/jupyter/labextensions/datawhys_experimental_control/static/third-party-licenses.json
datawhys_experimental_control-0.1.2.data/data/share/jupyter/labextensions/datawhys_experimental_control/install.json
datawhys_experimental_control-0.1.2.dist-info/METADATA
datawhys_experimental_control-0.1.2.dist-info/WHEEL
datawhys_experimental_control-0.1.2.dist-info/licenses/LICENSE
datawhys_experimental_control-0.1.2.dist-info/RECORD
