Metadata-Version: 2.4
Name: datawhys_experimental_control
Version: 0.1.2
Summary: A JupyterLab extension that locks down the user interface and provides additional controls for running experiments using the JupyterLab platform. It is not configurable but may serve as an example for other projects.
Project-URL: Homepage, https://github.com/aolney/datawhys-experimental-control
Project-URL: Bug Tracker, https://github.com/aolney/datawhys-experimental-control/issues
Project-URL: Repository, https://github.com/aolney/datawhys-experimental-control.git
Author-email: datawhys-experimental-control <aolney@memphis.edu>
License:                                  Apache License
License-File: LICENSE
Keywords: jupyter,jupyterlab,jupyterlab-extension
Classifier: Framework :: Jupyter
Classifier: Framework :: Jupyter :: JupyterLab
Classifier: Framework :: Jupyter :: JupyterLab :: 4
Classifier: Framework :: Jupyter :: JupyterLab :: Extensions
Classifier: Framework :: Jupyter :: JupyterLab :: Extensions :: Prebuilt
Classifier: License :: OSI Approved :: BSD License
Classifier: Programming Language :: Python
Classifier: Programming Language :: Python :: 3
Classifier: Programming Language :: Python :: 3.9
Classifier: Programming Language :: Python :: 3.10
Classifier: Programming Language :: Python :: 3.11
Classifier: Programming Language :: Python :: 3.12
Classifier: Programming Language :: Python :: 3.13
Requires-Python: >=3.9
